feishu/README.md
feishu/__init__.py
feishu/_version.py
feishu/exceptions.py
feishu/py.typed
feishu/variables.py
feishu/auth/__init__.py
feishu/auth/app_access_token.py
feishu/auth/tenant_access_token.py
feishu/im/__init__.py
feishu/im/messages.py
feishu/im/messages.pyi
feishu/im/utils.py
feishu/robot/__init__.py
feishu/robot/chat.py
feishu/robot/chat.pyi
feishu/robot/verification.py
feishu/third_party/__init__.py
feishu/third_party/openai.py
feishu/utils/__init__.py
feishu/utils/async_request.py
feishu/utils/crypto.py
feishu/utils/decorators.py
feishu/utils/request.py
open_feishu-0.0.5.dist-info/LICENSE
open_feishu-0.0.5.dist-info/LICENSE.header
open_feishu-0.0.5.dist-info/METADATA
open_feishu-0.0.5.dist-info/WHEEL
open_feishu-0.0.5.dist-info/top_level.txt
open_feishu-0.0.5.dist-info/RECORD
