Metadata-Version: 2.1
Name: open-feishu
Version: 0.0.5
Summary: Python SDK for Feishu / Lark
Author-email: Zhiyuan Chen <this@zyc.ai>
Maintainer-email: Zhiyuan Chen <this@zyc.ai>
License: GNU AFFERO GENERAL PUBLIC LICENSE
Project-URL: documentation, https://feishu.danling.org
Project-URL: homepage, https://feishu.danling.org
Project-URL: repository, https://github.com/ZhiyuanChen/open-feishu
Keywords: deep-learning,DNA,machine-learning,Protein,RNA
Classifier: Development Status :: 2 - Pre-Alpha 
Classifier: Intended Audience :: Developers
Classifier: Intended Audience :: Education
Classifier: Intended Audience :: Science/Research
Classifier: License :: OSI Approved :: GNU Affero General Public License v3 or later (AGPLv3+)
Classifier: Operating System :: OS Independent
Classifier: Programming Language :: Python :: 3 :: Only
Classifier: Programming Language :: Python :: 3.7
Classifier: Programming Language :: Python :: 3.8
Classifier: Programming Language :: Python :: 3.9
Classifier: Programming Language :: Python :: 3.10
Classifier: Programming Language :: Python :: 3.11
Classifier: Programming Language :: Python :: 3.12
Classifier: Topic :: Scientific/Engineering :: Artificial Intelligence
Requires-Python: >=3.7
License-File: LICENSE
License-File: LICENSE.header
Requires-Dist: asyncio
Requires-Dist: attrs
Requires-Dist: chanfig >=0.0.102
Requires-Dist: httpx
Requires-Dist: lazy-imports
Requires-Dist: pycryptodome
Requires-Dist: pytz
Requires-Dist: tzlocal
